windowsget_pdm/__init__.py
windowsget_pdm/cli.py
windowsget_pdm/downloader.py
windowsget_pdm/logger.py
windowsget_pdm-0.0.1.dist-info/METADATA
windowsget_pdm-0.0.1.dist-info/WHEEL
windowsget_pdm-0.0.1.dist-info/entry_points.txt
windowsget_pdm-0.0.1.dist-info/top_level.txt
windowsget_pdm-0.0.1.dist-info/RECORD
